coaxial_terminal_ai-0.6.8.dist-info/licenses/LICENSE
terminalai/__init__.py
terminalai/ai_providers.py
terminalai/ai_test_command_extraction.py
terminalai/cli_interaction.py
terminalai/clipboard_utils.py
terminalai/color_utils.py
terminalai/command_extraction.py
terminalai/command_utils.py
terminalai/config.py
terminalai/file_reader.py
terminalai/formatting.py
terminalai/query_utils.py
terminalai/shell_integration.py
terminalai/terminalai_cli.py
terminalai/test_command_extraction.py
coaxial_terminal_ai-0.6.8.dist-info/METADATA
coaxial_terminal_ai-0.6.8.dist-info/WHEEL
coaxial_terminal_ai-0.6.8.dist-info/entry_points.txt
coaxial_terminal_ai-0.6.8.dist-info/top_level.txt
coaxial_terminal_ai-0.6.8.dist-info/RECORD
