Metadata-Version: 2.4
Name: coaxial-terminal-ai
Version: 0.6.8
Summary: TerminalAI: Command-line AI assistant
Author-email: coaxialdolor <your.email@example.com>
License-Expression: MIT
Project-URL: Homepage, https://github.com/coaxialdolor/terminalai
Project-URL: Bug Tracker, https://github.com/coaxialdolor/terminalai/issues
Classifier: Development Status :: 4 - Beta
Classifier: Environment :: Console
Classifier: Intended Audience :: Developers
Classifier: Intended Audience :: System Administrators
Classifier: Programming Language :: Python :: 3
Classifier: Programming Language :: Python :: 3.8
Classifier: Programming Language :: Python :: 3.9
Classifier: Programming Language :: Python :: 3.10
Classifier: Programming Language :: Python :: 3.11
Classifier: Programming Language :: Python :: 3.12
Classifier: Operating System :: OS Independent
Classifier: Topic :: Utilities
Requires-Python: >=3.8
License-File: LICENSE
Requires-Dist: requests
Requires-Dist: pygments
Requires-Dist: rich
Requires-Dist: pyperclip
Requires-Dist: appdirs
Dynamic: license-file
